design_pytterns/__init__.py
design_pytterns/_about.py
design_pytterns/_helpers/__init__.py
design_pytterns/_helpers/concrete_subclass_register.py
design_pytterns/errors/__init__.py
design_pytterns/errors/design_pyttern_error.py
design_pytterns/errors/invalid_class_id_error.py
design_pytterns/errors/unhashable_class_id_error.py
design_pytterns/errors/unidentifiable_subclass_error.py
design_pytterns/errors/unregistered_class_id_error.py
design_pytterns/factory/__init__.py
design_pytterns/factory/factory.py
design_pytterns/factory/subclass_factory.py
design_pytterns/interfaces/__init__.py
design_pytterns/interfaces/subclass_identifiable.py
design_pytterns/observer/__init__.py
design_pytterns/observer/event_publisher.py
design_pytterns/observer/publisher.py
design_pytterns/observer/subscriber.py
design_pytterns/singleton/__init__.py
design_pytterns/singleton/singleton.py
design_pytterns/singleton/singleton_meta.py
design_pytterns-0.6.0.dist-info/METADATA
design_pytterns-0.6.0.dist-info/WHEEL
design_pytterns-0.6.0.dist-info/top_level.txt
design_pytterns-0.6.0.dist-info/RECORD
