Metadata-Version: 2.1
Name: design-pytterns
Version: 0.6.0
Summary: Implementation of Basic Python Design Patters
Home-page: https://github.com/Alchemy-Meister/python-design-patterns
Author: Alchemy-Meister
Author-email: meister.alchemy@gmail.com
License: GPL-3.0-or-later
Keywords: Design Patterns,Singleton,Factory,Observer
Platform: UNKNOWN
Classifier: Development Status :: 2 - Pre-Alpha
Classifier: License :: OSI Approved :: GNU General Public License v3 or later (GPLv3+)
Classifier: Programming Language :: Python :: 3.7
Classifier: Programming Language :: Python :: 3.8
Classifier: Programming Language :: Python :: 3.9
Classifier: Intended Audience :: Developers
Classifier: Operating System :: OS Independent
Provides-Extra: tests
Requires-Dist: coverage ; extra == 'tests'
Requires-Dist: pytest ; extra == 'tests'
Requires-Dist: pytest-cov ; extra == 'tests'
